ansible/module_utils/hashivault.py
ansible/modules/hashivault/__init__.py
ansible/modules/hashivault/hashivault_approle_role_create.py
ansible/modules/hashivault/hashivault_approle_role_get.py
ansible/modules/hashivault/hashivault_approle_role_id.py
ansible/modules/hashivault/hashivault_approle_role_list.py
ansible/modules/hashivault/hashivault_approle_role_secret_accessor_get.py
ansible/modules/hashivault/hashivault_approle_role_secret_create.py
ansible/modules/hashivault/hashivault_approle_role_secret_delete.py
ansible/modules/hashivault/hashivault_approle_role_secret_get.py
ansible/modules/hashivault/hashivault_approle_role_secret_list.py
ansible/modules/hashivault/hashivault_audit_enable.py
ansible/modules/hashivault/hashivault_audit_list.py
ansible/modules/hashivault/hashivault_auth_enable.py
ansible/modules/hashivault/hashivault_auth_list.py
ansible/modules/hashivault/hashivault_aws_ec2_role_create.py
ansible/modules/hashivault/hashivault_cluster_status.py
ansible/modules/hashivault/hashivault_delete.py
ansible/modules/hashivault/hashivault_generate_root.py
ansible/modules/hashivault/hashivault_generate_root_cancel.py
ansible/modules/hashivault/hashivault_generate_root_init.py
ansible/modules/hashivault/hashivault_generate_root_status.py
ansible/modules/hashivault/hashivault_identity_entity.py
ansible/modules/hashivault/hashivault_identity_entity_alias.py
ansible/modules/hashivault/hashivault_init.py
ansible/modules/hashivault/hashivault_leader.py
ansible/modules/hashivault/hashivault_list.py
ansible/modules/hashivault/hashivault_mount_tune.py
ansible/modules/hashivault/hashivault_policy_delete.py
ansible/modules/hashivault/hashivault_policy_get.py
ansible/modules/hashivault/hashivault_policy_list.py
ansible/modules/hashivault/hashivault_policy_set.py
ansible/modules/hashivault/hashivault_policy_set_from_file.py
ansible/modules/hashivault/hashivault_read.py
ansible/modules/hashivault/hashivault_read_to_file.py
ansible/modules/hashivault/hashivault_rekey.py
ansible_modules_hashivault-3.17.1.dist-info/AUTHORS
ansible_modules_hashivault-3.17.1.dist-info/LICENSE
ansible_modules_hashivault-3.17.1.dist-info/METADATA
ansible_modules_hashivault-3.17.1.dist-info/WHEEL
ansible_modules_hashivault-3.17.1.dist-info/top_level.txt
ansible_modules_hashivault-3.17.1.dist-info/RECORD
