Metadata-Version: 2.1
Name: ansible-modules-hashivault
Version: 3.17.1
Summary: Ansible Modules for Hashicorp Vault
Home-page: https://github.com/TerryHowe/ansible-modules-hashivault
Author: Terry Howe
Author-email: terrylhowe@example.com
License: UNKNOWN
Platform: UNKNOWN
Requires-Dist: ansible (>=2.0.0)
Requires-Dist: hvac (>=0.7.0)
Requires-Dist: requests
